{"expireTime":9007200985934161000,"key":"gatsby-plugin-mdx-entire-payload-cc2ab08f3dfd95f77f7f723b5f017e01--undefined","val":{"mdast":{"type":"root","children":[{"type":"heading","depth":1,"children":[{"type":"text","value":"Heading 1","position":{"start":{"line":2,"column":3,"offset":3},"end":{"line":2,"column":12,"offset":12},"indent":[]}}],"position":{"start":{"line":2,"column":1,"offset":1},"end":{"line":2,"column":12,"offset":12},"indent":[]}},{"type":"heading","depth":2,"children":[{"type":"text","value":"Heading 2","position":{"start":{"line":4,"column":4,"offset":17},"end":{"line":4,"column":13,"offset":26},"indent":[]}}],"position":{"start":{"line":4,"column":1,"offset":14},"end":{"line":4,"column":13,"offset":26},"indent":[]}},{"type":"heading","depth":3,"children":[{"type":"text","value":"Heading 3","position":{"start":{"line":6,"column":5,"offset":32},"end":{"line":6,"column":14,"offset":41},"indent":[]}}],"position":{"start":{"line":6,"column":1,"offset":28},"end":{"line":6,"column":14,"offset":41},"indent":[]}},{"type":"heading","depth":4,"children":[{"type":"text","value":"Heading 4","position":{"start":{"line":8,"column":6,"offset":48},"end":{"line":8,"column":15,"offset":57},"indent":[]}}],"position":{"start":{"line":8,"column":1,"offset":43},"end":{"line":8,"column":15,"offset":57},"indent":[]}},{"type":"heading","depth":5,"children":[{"type":"text","value":"Heading 5","position":{"start":{"line":10,"column":7,"offset":65},"end":{"line":10,"column":16,"offset":74},"indent":[]}}],"position":{"start":{"line":10,"column":1,"offset":59},"end":{"line":10,"column":16,"offset":74},"indent":[]}},{"type":"heading","depth":6,"children":[{"type":"text","value":"Heading 6","position":{"start":{"line":12,"column":8,"offset":83},"end":{"line":12,"column":17,"offset":92},"indent":[]}}],"position":{"start":{"line":12,"column":1,"offset":76},"end":{"line":12,"column":17,"offset":92},"indent":[]}},{"type":"paragraph","children":[{"type":"strong","children":[{"type":"text","value":"bold text","position":{"start":{"line":14,"column":3,"offset":96},"end":{"line":14,"column":12,"offset":105},"indent":[]}}],"position":{"start":{"line":14,"column":1,"offset":94},"end":{"line":14,"column":14,"offset":107},"indent":[]}}],"position":{"start":{"line":14,"column":1,"offset":94},"end":{"line":14,"column":14,"offset":107},"indent":[]}},{"type":"paragraph","children":[{"type":"emphasis","children":[{"type":"text","value":"italicized text","position":{"start":{"line":16,"column":2,"offset":110},"end":{"line":16,"column":17,"offset":125},"indent":[]}}],"position":{"start":{"line":16,"column":1,"offset":109},"end":{"line":16,"column":18,"offset":126},"indent":[]}}],"position":{"start":{"line":16,"column":1,"offset":109},"end":{"line":16,"column":18,"offset":126},"indent":[]}},{"type":"blockquote","children":[{"type":"paragraph","children":[{"type":"text","value":"blockquote","position":{"start":{"line":18,"column":3,"offset":130},"end":{"line":18,"column":13,"offset":140},"indent":[]}}],"position":{"start":{"line":18,"column":3,"offset":130},"end":{"line":18,"column":13,"offset":140},"indent":[]}}],"position":{"start":{"line":18,"column":1,"offset":128},"end":{"line":18,"column":13,"offset":140},"indent":[]}},{"type":"list","ordered":true,"start":1,"spread":false,"children":[{"type":"listItem","spread":false,"checked":null,"children":[{"type":"paragraph","children":[{"type":"text","value":"First item","position":{"start":{"line":20,"column":4,"offset":145},"end":{"line":20,"column":14,"offset":155},"indent":[]}}],"position":{"start":{"line":20,"column":4,"offset":145},"end":{"line":20,"column":14,"offset":155},"indent":[]}}],"position":{"start":{"line":20,"column":1,"offset":142},"end":{"line":20,"column":14,"offset":155},"indent":[]}},{"type":"listItem","spread":false,"checked":null,"children":[{"type":"paragraph","children":[{"type":"text","value":"Second item","position":{"start":{"line":21,"column":4,"offset":159},"end":{"line":21,"column":15,"offset":170},"indent":[]}}],"position":{"start":{"line":21,"column":4,"offset":159},"end":{"line":21,"column":15,"offset":170},"indent":[]}}],"position":{"start":{"line":21,"column":1,"offset":156},"end":{"line":21,"column":15,"offset":170},"indent":[]}},{"type":"listItem","spread":false,"checked":null,"children":[{"type":"paragraph","children":[{"type":"text","value":"Third item","position":{"start":{"line":22,"column":4,"offset":174},"end":{"line":22,"column":14,"offset":184},"indent":[]}}],"position":{"start":{"line":22,"column":4,"offset":174},"end":{"line":22,"column":14,"offset":184},"indent":[]}}],"position":{"start":{"line":22,"column":1,"offset":171},"end":{"line":22,"column":14,"offset":184},"indent":[]}}],"position":{"start":{"line":20,"column":1,"offset":142},"end":{"line":22,"column":14,"offset":184},"indent":[1,1]}},{"type":"list","ordered":false,"start":null,"spread":false,"children":[{"type":"listItem","spread":false,"checked":null,"children":[{"type":"paragraph","children":[{"type":"text","value":"First item","position":{"start":{"line":24,"column":3,"offset":188},"end":{"line":24,"column":13,"offset":198},"indent":[]}}],"position":{"start":{"line":24,"column":3,"offset":188},"end":{"line":24,"column":13,"offset":198},"indent":[]}}],"position":{"start":{"line":24,"column":1,"offset":186},"end":{"line":24,"column":13,"offset":198},"indent":[]}},{"type":"listItem","spread":false,"checked":null,"children":[{"type":"paragraph","children":[{"type":"text","value":"Second item","position":{"start":{"line":25,"column":3,"offset":201},"end":{"line":25,"column":14,"offset":212},"indent":[]}}],"position":{"start":{"line":25,"column":3,"offset":201},"end":{"line":25,"column":14,"offset":212},"indent":[]}}],"position":{"start":{"line":25,"column":1,"offset":199},"end":{"line":25,"column":14,"offset":212},"indent":[]}},{"type":"listItem","spread":false,"checked":null,"children":[{"type":"paragraph","children":[{"type":"text","value":"Third item","position":{"start":{"line":26,"column":3,"offset":215},"end":{"line":26,"column":13,"offset":225},"indent":[]}}],"position":{"start":{"line":26,"column":3,"offset":215},"end":{"line":26,"column":13,"offset":225},"indent":[]}}],"position":{"start":{"line":26,"column":1,"offset":213},"end":{"line":26,"column":13,"offset":225},"indent":[]}}],"position":{"start":{"line":24,"column":1,"offset":186},"end":{"line":26,"column":13,"offset":225},"indent":[1,1]}},{"type":"paragraph","children":[{"type":"link","title":null,"url":"https://www.example.com","children":[{"type":"text","value":"title","position":{"start":{"line":28,"column":2,"offset":228},"end":{"line":28,"column":7,"offset":233},"indent":[]}}],"position":{"start":{"line":28,"column":1,"offset":227},"end":{"line":28,"column":33,"offset":259},"indent":[]}}],"position":{"start":{"line":28,"column":1,"offset":227},"end":{"line":28,"column":33,"offset":259},"indent":[]}},{"type":"paragraph","children":[{"type":"image","title":null,"url":"image.jpg","alt":"alt text","position":{"start":{"line":30,"column":1,"offset":261},"end":{"line":30,"column":23,"offset":283},"indent":[]}}],"position":{"start":{"line":30,"column":1,"offset":261},"end":{"line":30,"column":23,"offset":283},"indent":[]}},{"type":"table","align":[null,null],"children":[{"type":"tableRow","children":[{"type":"tableCell","children":[{"type":"text","value":"Syntax","position":{"start":{"line":32,"column":3,"offset":287},"end":{"line":32,"column":9,"offset":293},"indent":[]}}],"position":{"start":{"line":32,"column":3,"offset":287},"end":{"line":32,"column":12,"offset":296},"indent":[]}},{"type":"tableCell","children":[{"type":"text","value":"Description","position":{"start":{"line":32,"column":15,"offset":299},"end":{"line":32,"column":26,"offset":310},"indent":[]}}],"position":{"start":{"line":32,"column":15,"offset":299},"end":{"line":32,"column":26,"offset":310},"indent":[]}}],"position":{"start":{"line":32,"column":1,"offset":285},"end":{"line":32,"column":28,"offset":312},"indent":[]}},{"type":"tableRow","children":[{"type":"tableCell","children":[{"type":"text","value":"Header","position":{"start":{"line":34,"column":3,"offset":343},"end":{"line":34,"column":9,"offset":349},"indent":[]}}],"position":{"start":{"line":34,"column":3,"offset":343},"end":{"line":34,"column":12,"offset":352},"indent":[]}},{"type":"tableCell","children":[{"type":"text","value":"Title","position":{"start":{"line":34,"column":15,"offset":355},"end":{"line":34,"column":20,"offset":360},"indent":[]}}],"position":{"start":{"line":34,"column":15,"offset":355},"end":{"line":34,"column":26,"offset":366},"indent":[]}}],"position":{"start":{"line":34,"column":1,"offset":341},"end":{"line":34,"column":28,"offset":368},"indent":[]}},{"type":"tableRow","children":[{"type":"tableCell","children":[{"type":"text","value":"Paragraph","position":{"start":{"line":35,"column":3,"offset":371},"end":{"line":35,"column":12,"offset":380},"indent":[]}}],"position":{"start":{"line":35,"column":3,"offset":371},"end":{"line":35,"column":12,"offset":380},"indent":[]}},{"type":"tableCell","children":[{"type":"text","value":"Text","position":{"start":{"line":35,"column":15,"offset":383},"end":{"line":35,"column":19,"offset":387},"indent":[]}}],"position":{"start":{"line":35,"column":15,"offset":383},"end":{"line":35,"column":26,"offset":394},"indent":[]}}],"position":{"start":{"line":35,"column":1,"offset":369},"end":{"line":35,"column":28,"offset":396},"indent":[]}}],"position":{"start":{"line":32,"column":1,"offset":285},"end":{"line":35,"column":28,"offset":396},"indent":[1,1,1]}},{"type":"paragraph","children":[{"type":"text","value":"{\n\"firstName\": \"John\",\n\"lastName\": \"Smith\",\n\"age\": 25\n}","position":{"start":{"line":37,"column":1,"offset":398},"end":{"line":41,"column":2,"offset":453},"indent":[1,1,1,1]}}],"position":{"start":{"line":37,"column":1,"offset":398},"end":{"line":41,"column":2,"offset":453},"indent":[1,1,1,1]}},{"type":"code","lang":"html","meta":null,"value":"(function someDemo() { var test = \"Hello World!\"; console.log(test); })(); return () => <App />;","position":{"start":{"line":43,"column":1,"offset":455},"end":{"line":45,"column":4,"offset":563},"indent":[1,1]}},{"type":"export","value":"export const _frontmatter = {\"title\":\"First Project\",\"slug\":\"first-project\",\"date\":\"2020-03-21T00:00:00.000Z\",\"featureImage\":\"bwPhoto.jpg\",\"excerpt\":\"This is my first project\",\"github\":\"This is my first project\"}","position":{"start":{"line":48,"column":1,"offset":566},"end":{"line":48,"column":213,"offset":778},"indent":[]}}],"position":{"start":{"line":1,"column":1,"offset":0},"end":{"line":48,"column":213,"offset":778}}},"scopeImports":["import * as React from 'react'"],"scopeIdentifiers":["React"],"body":"var _excluded = [\"components\"];\nfunction _extends() { _extends = Object.assign ? Object.assign.bind() : function (target) { for (var i = 1; i < arguments.length; i++) { var source = arguments[i]; for (var key in source) { if (Object.prototype.hasOwnProperty.call(source, key)) { target[key] = source[key]; } } } return target; }; return _extends.apply(this, arguments); }\nfunction _objectWithoutProperties(source, excluded) { if (source == null) return {}; var target = _objectWithoutPropertiesLoose(source, excluded); var key, i; if (Object.getOwnPropertySymbols) { var sourceSymbolKeys = Object.getOwnPropertySymbols(source); for (i = 0; i < sourceSymbolKeys.length; i++) { key = sourceSymbolKeys[i]; if (excluded.indexOf(key) >= 0) continue; if (!Object.prototype.propertyIsEnumerable.call(source, key)) continue; target[key] = source[key]; } } return target; }\nfunction _objectWithoutPropertiesLoose(source, excluded) { if (source == null) return {}; var target = {}; var sourceKeys = Object.keys(source); var key, i; for (i = 0; i < sourceKeys.length; i++) { key = sourceKeys[i]; if (excluded.indexOf(key) >= 0) continue; target[key] = source[key]; } return target; }\n/* @jsxRuntime classic */\n/* @jsx mdx */\n\nvar _frontmatter = {\n  \"title\": \"First Project\",\n  \"slug\": \"first-project\",\n  \"date\": \"2020-03-21T00:00:00.000Z\",\n  \"featureImage\": \"bwPhoto.jpg\",\n  \"excerpt\": \"This is my first project\",\n  \"github\": \"This is my first project\"\n};\nvar layoutProps = {\n  _frontmatter: _frontmatter\n};\nvar MDXLayout = \"wrapper\";\nreturn function MDXContent(_ref) {\n  var components = _ref.components,\n    props = _objectWithoutProperties(_ref, _excluded);\n  return mdx(MDXLayout, _extends({}, layoutProps, props, {\n    components: components,\n    mdxType: \"MDXLayout\"\n  }), mdx(\"h1\", null, \"Heading 1\"), mdx(\"h2\", null, \"Heading 2\"), mdx(\"h3\", null, \"Heading 3\"), mdx(\"h4\", null, \"Heading 4\"), mdx(\"h5\", null, \"Heading 5\"), mdx(\"h6\", null, \"Heading 6\"), mdx(\"p\", null, mdx(\"strong\", {\n    parentName: \"p\"\n  }, \"bold text\")), mdx(\"p\", null, mdx(\"em\", {\n    parentName: \"p\"\n  }, \"italicized text\")), mdx(\"blockquote\", null, mdx(\"p\", {\n    parentName: \"blockquote\"\n  }, \"blockquote\")), mdx(\"ol\", null, mdx(\"li\", {\n    parentName: \"ol\"\n  }, \"First item\"), mdx(\"li\", {\n    parentName: \"ol\"\n  }, \"Second item\"), mdx(\"li\", {\n    parentName: \"ol\"\n  }, \"Third item\")), mdx(\"ul\", null, mdx(\"li\", {\n    parentName: \"ul\"\n  }, \"First item\"), mdx(\"li\", {\n    parentName: \"ul\"\n  }, \"Second item\"), mdx(\"li\", {\n    parentName: \"ul\"\n  }, \"Third item\")), mdx(\"p\", null, mdx(\"a\", {\n    parentName: \"p\",\n    \"href\": \"https://www.example.com\"\n  }, \"title\")), mdx(\"p\", null, mdx(\"span\", {\n    parentName: \"p\",\n    \"className\": \"gatsby-resp-image-wrapper\",\n    \"style\": {\n      \"position\": \"relative\",\n      \"display\": \"block\",\n      \"marginLeft\": \"auto\",\n      \"marginRight\": \"auto\",\n      \"maxWidth\": \"590px\"\n    }\n  }, \"\\n      \", mdx(\"span\", {\n    parentName: \"span\",\n    \"className\": \"gatsby-resp-image-background-image\",\n    \"style\": {\n      \"paddingBottom\": \"66.21621621621621%\",\n      \"position\": \"relative\",\n      \"bottom\": \"0\",\n      \"left\": \"0\",\n      \"backgroundImage\": \"url('data:image/jpeg;base64,/9j/2wBDABALDA4MChAODQ4SERATGCgaGBYWGDEjJR0oOjM9PDkzODdASFxOQERXRTc4UG1RV19iZ2hnPk1xeXBkeFxlZ2P/2wBDARESEhgVGC8aGi9jQjhCY2NjY2NjY2NjY2NjY2NjY2NjY2NjY2NjY2NjY2NjY2NjY2NjY2NjY2NjY2NjY2NjY2P/wgARCAANABQDASIAAhEBAxEB/8QAFgABAQEAAAAAAAAAAAAAAAAABAAF/8QAFAEBAAAAAAAAAAAAAAAAAAAAAP/aAAwDAQACEAMQAAABNoDSCtaP/8QAGxABAQACAwEAAAAAAAAAAAAAAQIAEQMSEyL/2gAIAQEAAQUC4dGWCMG4k6zP14mf/8QAFBEBAAAAAAAAAAAAAAAAAAAAEP/aAAgBAwEBPwE//8QAFBEBAAAAAAAAAAAAAAAAAAAAEP/aAAgBAgEBPwE//8QAGRAAAgMBAAAAAAAAAAAAAAAAACEBEBEx/9oACAEBAAY/AmK8Oyf/xAAaEAACAwEBAAAAAAAAAAAAAAAAAREhMVGB/9oACAEBAAE/IYqaaL6gxTBG6LfHCtX+n//aAAwDAQACAAMAAAAQUM//xAAUEQEAAAAAAAAAAAAAAAAAAAAQ/9oACAEDAQE/ED//xAAUEQEAAAAAAAAAAAAAAAAAAAAQ/9oACAECAQE/ED//xAAaEAEBAQEAAwAAAAAAAAAAAAABEQAhMUFh/9oACAEBAAE/EC12oQzWoNoxyU6+xyOlQlfFwVL7HTBgIXP/2Q==')\",\n      \"backgroundSize\": \"cover\",\n      \"display\": \"block\"\n    }\n  }), \"\\n  \", mdx(\"img\", {\n    parentName: \"span\",\n    \"className\": \"gatsby-resp-image-image\",\n    \"alt\": \"alt text\",\n    \"title\": \"alt text\",\n    \"src\": \"/static/114a4c9e7956fca0da9defe55e7d9af2/1c72d/image.jpg\",\n    \"srcSet\": [\"/static/114a4c9e7956fca0da9defe55e7d9af2/a80bd/image.jpg 148w\", \"/static/114a4c9e7956fca0da9defe55e7d9af2/1c91a/image.jpg 295w\", \"/static/114a4c9e7956fca0da9defe55e7d9af2/1c72d/image.jpg 590w\", \"/static/114a4c9e7956fca0da9defe55e7d9af2/a8a14/image.jpg 885w\", \"/static/114a4c9e7956fca0da9defe55e7d9af2/fbd2c/image.jpg 1180w\", \"/static/114a4c9e7956fca0da9defe55e7d9af2/3195e/image.jpg 3089w\"],\n    \"sizes\": \"(max-width: 590px) 100vw, 590px\",\n    \"style\": {\n      \"width\": \"100%\",\n      \"height\": \"100%\",\n      \"margin\": \"0\",\n      \"verticalAlign\": \"middle\",\n      \"position\": \"absolute\",\n      \"top\": \"0\",\n      \"left\": \"0\"\n    },\n    \"loading\": \"lazy\",\n    \"decoding\": \"async\"\n  }), \"\\n    \")), mdx(\"table\", null, mdx(\"thead\", {\n    parentName: \"table\"\n  }, mdx(\"tr\", {\n    parentName: \"thead\"\n  }, mdx(\"th\", {\n    parentName: \"tr\",\n    \"align\": null\n  }, \"Syntax\"), mdx(\"th\", {\n    parentName: \"tr\",\n    \"align\": null\n  }, \"Description\"))), mdx(\"tbody\", {\n    parentName: \"table\"\n  }, mdx(\"tr\", {\n    parentName: \"tbody\"\n  }, mdx(\"td\", {\n    parentName: \"tr\",\n    \"align\": null\n  }, \"Header\"), mdx(\"td\", {\n    parentName: \"tr\",\n    \"align\": null\n  }, \"Title\")), mdx(\"tr\", {\n    parentName: \"tbody\"\n  }, mdx(\"td\", {\n    parentName: \"tr\",\n    \"align\": null\n  }, \"Paragraph\"), mdx(\"td\", {\n    parentName: \"tr\",\n    \"align\": null\n  }, \"Text\")))), mdx(\"p\", null, \"{\\n\\\"firstName\\\": \\\"John\\\",\\n\\\"lastName\\\": \\\"Smith\\\",\\n\\\"age\\\": 25\\n}\"), mdx(\"pre\", null, mdx(\"code\", {\n    parentName: \"pre\",\n    \"className\": \"language-html\"\n  }, \"(function someDemo() { var test = \\\"Hello World!\\\"; console.log(test); })(); return () => <App />;\\n\")));\n}\n;\nMDXContent.isMDXComponent = true;","rawMDXOutput":"/* @jsx mdx */\nimport { mdx } from '@mdx-js/react';\n/* @jsxRuntime classic */\n/* @jsx mdx */\n\nexport const _frontmatter = {\n  \"title\": \"First Project\",\n  \"slug\": \"first-project\",\n  \"date\": \"2020-03-21T00:00:00.000Z\",\n  \"featureImage\": \"bwPhoto.jpg\",\n  \"excerpt\": \"This is my first project\",\n  \"github\": \"This is my first project\"\n};\n\nconst layoutProps = {\n  _frontmatter\n};\nconst MDXLayout = \"wrapper\"\nexport default function MDXContent({\n  components,\n  ...props\n}) {\n  return <MDXLayout {...layoutProps} {...props} components={components} mdxType=\"MDXLayout\">\n    <h1>{`Heading 1`}</h1>\n    <h2>{`Heading 2`}</h2>\n    <h3>{`Heading 3`}</h3>\n    <h4>{`Heading 4`}</h4>\n    <h5>{`Heading 5`}</h5>\n    <h6>{`Heading 6`}</h6>\n    <p><strong parentName=\"p\">{`bold text`}</strong></p>\n    <p><em parentName=\"p\">{`italicized text`}</em></p>\n    <blockquote>\n      <p parentName=\"blockquote\">{`blockquote`}</p>\n    </blockquote>\n    <ol>\n      <li parentName=\"ol\">{`First item`}</li>\n      <li parentName=\"ol\">{`Second item`}</li>\n      <li parentName=\"ol\">{`Third item`}</li>\n    </ol>\n    <ul>\n      <li parentName=\"ul\">{`First item`}</li>\n      <li parentName=\"ul\">{`Second item`}</li>\n      <li parentName=\"ul\">{`Third item`}</li>\n    </ul>\n    <p><a parentName=\"p\" {...{\n        \"href\": \"https://www.example.com\"\n      }}>{`title`}</a></p>\n    <p><span parentName=\"p\" {...{\n        \"className\": \"gatsby-resp-image-wrapper\",\n        \"style\": {\n          \"position\": \"relative\",\n          \"display\": \"block\",\n          \"marginLeft\": \"auto\",\n          \"marginRight\": \"auto\",\n          \"maxWidth\": \"590px\"\n        }\n      }}>{`\n      `}<span parentName=\"span\" {...{\n          \"className\": \"gatsby-resp-image-background-image\",\n          \"style\": {\n            \"paddingBottom\": \"66.21621621621621%\",\n            \"position\": \"relative\",\n            \"bottom\": \"0\",\n            \"left\": \"0\",\n            \"backgroundImage\": \"url('data:image/jpeg;base64,/9j/2wBDABALDA4MChAODQ4SERATGCgaGBYWGDEjJR0oOjM9PDkzODdASFxOQERXRTc4UG1RV19iZ2hnPk1xeXBkeFxlZ2P/2wBDARESEhgVGC8aGi9jQjhCY2NjY2NjY2NjY2NjY2NjY2NjY2NjY2NjY2NjY2NjY2NjY2NjY2NjY2NjY2NjY2NjY2P/wgARCAANABQDASIAAhEBAxEB/8QAFgABAQEAAAAAAAAAAAAAAAAABAAF/8QAFAEBAAAAAAAAAAAAAAAAAAAAAP/aAAwDAQACEAMQAAABNoDSCtaP/8QAGxABAQACAwEAAAAAAAAAAAAAAQIAEQMSEyL/2gAIAQEAAQUC4dGWCMG4k6zP14mf/8QAFBEBAAAAAAAAAAAAAAAAAAAAEP/aAAgBAwEBPwE//8QAFBEBAAAAAAAAAAAAAAAAAAAAEP/aAAgBAgEBPwE//8QAGRAAAgMBAAAAAAAAAAAAAAAAACEBEBEx/9oACAEBAAY/AmK8Oyf/xAAaEAACAwEBAAAAAAAAAAAAAAAAAREhMVGB/9oACAEBAAE/IYqaaL6gxTBG6LfHCtX+n//aAAwDAQACAAMAAAAQUM//xAAUEQEAAAAAAAAAAAAAAAAAAAAQ/9oACAEDAQE/ED//xAAUEQEAAAAAAAAAAAAAAAAAAAAQ/9oACAECAQE/ED//xAAaEAEBAQEAAwAAAAAAAAAAAAABEQAhMUFh/9oACAEBAAE/EC12oQzWoNoxyU6+xyOlQlfFwVL7HTBgIXP/2Q==')\",\n            \"backgroundSize\": \"cover\",\n            \"display\": \"block\"\n          }\n        }}></span>{`\n  `}<img parentName=\"span\" {...{\n          \"className\": \"gatsby-resp-image-image\",\n          \"alt\": \"alt text\",\n          \"title\": \"alt text\",\n          \"src\": \"/static/114a4c9e7956fca0da9defe55e7d9af2/1c72d/image.jpg\",\n          \"srcSet\": [\"/static/114a4c9e7956fca0da9defe55e7d9af2/a80bd/image.jpg 148w\", \"/static/114a4c9e7956fca0da9defe55e7d9af2/1c91a/image.jpg 295w\", \"/static/114a4c9e7956fca0da9defe55e7d9af2/1c72d/image.jpg 590w\", \"/static/114a4c9e7956fca0da9defe55e7d9af2/a8a14/image.jpg 885w\", \"/static/114a4c9e7956fca0da9defe55e7d9af2/fbd2c/image.jpg 1180w\", \"/static/114a4c9e7956fca0da9defe55e7d9af2/3195e/image.jpg 3089w\"],\n          \"sizes\": \"(max-width: 590px) 100vw, 590px\",\n          \"style\": {\n            \"width\": \"100%\",\n            \"height\": \"100%\",\n            \"margin\": \"0\",\n            \"verticalAlign\": \"middle\",\n            \"position\": \"absolute\",\n            \"top\": \"0\",\n            \"left\": \"0\"\n          },\n          \"loading\": \"lazy\",\n          \"decoding\": \"async\"\n        }}></img>{`\n    `}</span></p>\n    <table>\n      <thead parentName=\"table\">\n        <tr parentName=\"thead\">\n          <th parentName=\"tr\" {...{\n            \"align\": null\n          }}>{`Syntax`}</th>\n          <th parentName=\"tr\" {...{\n            \"align\": null\n          }}>{`Description`}</th>\n        </tr>\n      </thead>\n      <tbody parentName=\"table\">\n        <tr parentName=\"tbody\">\n          <td parentName=\"tr\" {...{\n            \"align\": null\n          }}>{`Header`}</td>\n          <td parentName=\"tr\" {...{\n            \"align\": null\n          }}>{`Title`}</td>\n        </tr>\n        <tr parentName=\"tbody\">\n          <td parentName=\"tr\" {...{\n            \"align\": null\n          }}>{`Paragraph`}</td>\n          <td parentName=\"tr\" {...{\n            \"align\": null\n          }}>{`Text`}</td>\n        </tr>\n      </tbody>\n    </table>\n    <p>{`{\n\"firstName\": \"John\",\n\"lastName\": \"Smith\",\n\"age\": 25\n}`}</p>\n    <pre><code parentName=\"pre\" {...{\n        \"className\": \"language-html\"\n      }}>{`(function someDemo() { var test = \"Hello World!\"; console.log(test); })(); return () => <App />;\n`}</code></pre>\n\n    </MDXLayout>;\n}\n;\nMDXContent.isMDXComponent = true;"}}